{
    "elem": {
        "x1": [],
        "x2": [],
        "y1": [
            {
                "qname": "y1",
                "text": null,
                "tail": null,
                "ns_map": {
                    "xsi": "http://www.w3.org/2001/XMLSchema-instance"
                },
                "children": [],
                "attributes": {}
            }
        ],
        "y2": [
            {
                "qname": "y2",
                "text": null,
                "tail": null,
                "ns_map": {
                    "xsi": "http://www.w3.org/2001/XMLSchema-instance"
                },
                "children": [],
                "attributes": {}
            }
        ]
    }
}