{
    "str00AA": "a",
    "str10-M": "b",
    "str20Z": "c",
    "str01Aa": "a",
    "str11-d": "b",
    "str21h": "c",
    "str02Aj": "a",
    "str12-r": "b",
    "str22z": "c",
    "str03A\u00c0": "a",
    "str13-\u00cb": "b",
    "str23\u00d6": "c",
    "str04A\u00d8": "a",
    "str14-\u00db": "b",
    "str24\u00de": "c",
    "str05A\u00e0": "a",
    "str15-\u00eb": "b",
    "str25\u00f6": "c",
    "str06A\u00f8": "a",
    "str16-\u00fb": "b",
    "str26\u00ff": "c",
    "str07A\u0100": "a",
    "str17-\u0118": "b",
    "str27\u0131": "c",
    "str08A\u0134": "a",
    "str18-\u0139": "b",
    "str28\u013e": "c",
    "str09A\u0141": "a",
    "str19-\u0144": "b",
    "str29\u0148": "c"
}