<!-- xsdata instance -->
<test:root xmlns:test="SType/ST_facets" xmlns:xsi="http://www.w3.org/2001/XMLSchema-instance">
  <value>a00&#4523;</value>
  <value>a10&#4526;</value>
  <value>a1-&#4526;</value>
  <value>a1A&#4527;</value>
  <value>a20&#4535;</value>
  <value>a2-&#4535;</value>
  <value>a2A&#4536;</value>
  <value>a30&#4538;</value>
  <value>a40&#4540;</value>
  <value>a4-&#4543;</value>
  <value>a4A&#4546;</value>
  <value>a50&#4587;</value>
  <value>a60&#4592;</value>
  <value>a70&#4601;</value>
  <value>a80&#7680;</value>
  <value>a8-&#7754;</value>
  <value>a8A&#7829;</value>
  <value>a90&#7835;</value>
</test:root>
